clmystes_podsearch/__init__.py
clmystes_podsearch-0.1.0.dist-info/WHEEL
clmystes_podsearch-0.1.0.dist-info/METADATA
clmystes_podsearch-0.1.0.dist-info/RECORD
