Metadata-Version: 2.1
Name: clmystes_podsearch
Version: 0.1.0
Summary: Let's find some podcasts!
Home-page: https://github.com/clmystes/podsearch
Author: clmystes
Author-email: clmystes@gmail.com
Classifier: License :: OSI Approved :: MIT License
